mklog/__init__.py
mklog/__main__.py
mklog/errors.py
mklog-1.4.0.dist-info/AUTHORS
mklog-1.4.0.dist-info/LICENSE
mklog-1.4.0.dist-info/METADATA
mklog-1.4.0.dist-info/WHEEL
mklog-1.4.0.dist-info/entry_points.txt
mklog-1.4.0.dist-info/top_level.txt
mklog-1.4.0.dist-info/zip-safe
mklog-1.4.0.dist-info/RECORD
