Metadata-Version: 2.1
Name: mklog
Version: 1.4.0
Summary: Append date and time before text
Home-page: http://framagit.org/spalax/mklog
Author: Louis Paternault
Author-email: spalax@gresille.org
License: GPLv3 or any later version
Project-URL: Documentation, http://mklog.readthedocs.io
Project-URL: Source, https://framagit.org/spalax/mklog
Project-URL: Tracker, https://framagit.org/spalax/mklog/issues
Keywords: log timestamp
Classifier: Development Status :: 5 - Production/Stable
Classifier: Environment :: Console
Classifier: Intended Audience :: System Administrators
Classifier: License :: OSI Approved :: GNU General Public License v3 or later (GPLv3+)
Classifier: Operating System :: Unix
Classifier: Programming Language :: Python
Classifier: Programming Language :: Python :: 3
Classifier: Programming Language :: Python :: 3.8
Classifier: Programming Language :: Python :: 3.9
Classifier: Programming Language :: Python :: 3.10
Classifier: Programming Language :: Python :: 3.11
Classifier: Programming Language :: Python :: 3.12
Classifier: Programming Language :: Python :: 3.13
Classifier: Topic :: System :: Logging
Requires-Python: <4,>=3.8
License-File: LICENSE
License-File: AUTHORS
